{
  "npcs": [
    2042,
    2043,
    2044
  ],
  "petItem": 12921,
  "petRarity": 1500,
  "guaranteed": [
    {
      "id": 12934,
      "min": 100,
      "max": 300
    },
    {
      "id": 12938,
      "min": 1,
      "max": 2
    }
  ],
  "tables": [
    {
      "name": "Unique",
      "tableweight": 1,
      "items": [
        {
          "id": 12922,
          "amount": 1,
          "weight": 1
        },
        {
          "id": 12932,
          "amount": 1,
          "weight": 1
        },
        {
          "id": 12927,
          "amount": 1,
          "weight": 1
        },
        {
          "id": 6571,
          "amount": 1,
          "weight": 1
        }
      ],
      "tables": []
    },
    {
      "name": "Armour",
      "tableweight": 7,
      "items": [
        {
          "id": 1149,
          "amount": 1,
          "weight": 1
        },
        {
          "id": 3204,
          "amount": 1,
          "weight": 1
        }
      ],
      "tables": []
    },
    {
      "name": "Runes",
      "tableweight": 32,
      "items": [
        {
          "id": 563,
          "amount": 200,
          "weight": 3
        },
        {
          "id": 560,
          "amount": 300,
          "weight": 1
        },
        {
          "id": 562,
          "amount": 500,
          "weight": 1
        },
        {
          "id": 7937,
          "amount": 1500,
          "weight": 1
        }
      ],
      "tables": []
    },
    {
      "name": "Herbs",
      "tableweight": 8,
      "items": [
        {
          "id": 2999,
          "amount": 25,
          "weight": 1
        },
        {
          "id": 3001,
          "amount": 10,
          "weight": 1
        },
        {
          "id": 268,
          "amount": 30,
          "weight": 1
        },
        {
          "id": 270,
          "amount": 10,
          "weight": 1
        }
      ],
      "tables": []
    },
    {
      "name": "Materials",
      "tableweight": 51,
      "items": [
        {
          "id": 1780,
          "amount": 1000,
          "weight": 3
        },
        {
          "id": 6290,
          "amount": 35,
          "weight": 3
        },
        {
          "id": 9193,
          "amount": 12,
          "weight": 3
        },
        {
          "id": 1516,
          "amount": 35,
          "weight": 3
        },
        {
          "id": 454,
          "amount": 200,
          "weight": 1
        },
        {
          "id": 452,
          "amount": 2,
          "weight": 1
        }
      ],
      "tables": []
    },
    {
      "name": "Seeds",
      "tableweight": 21,
      "items": [
        {
          "id": 5316,
          "amount": 1,
          "weight": 4
        },
        {
          "id": 5290,
          "amount": 2,
          "weight": 4
        },
        {
          "id": 5288,
          "amount": 3,
          "weight": 4
        },
        {
          "id": 5289,
          "amount": 1,
          "weight": 4
        },
        {
          "id": 5296,
          "amount": 2,
          "weight": 2
        },
        {
          "id": 5300,
          "amount": 1,
          "weight": 2
        },
        {
          "id": 5303,
          "amount": 2,
          "weight": 3
        },
        {
          "id": 5304,
          "amount": 1,
          "weight": 2
        },
        {
          "id": 5317,
          "amount": 1,
          "weight": 1
        },
        {
          "id": 4207,
          "amount": 1,
          "weight": 1
        }
      ],
      "tables": []
    },
    {
      "name": "Other",
      "tableweight": 46,
      "items": [],
      "tables": [
        {
          "name": "Normal",
          "weight": 500,
          "items": [
            {
              "id": 12938,
              "amount": 1,
              "weight": 5
            },
            {
              "id": 537,
              "amount": 12,
              "weight": 5
            },
            {
              "id": 5975,
              "amount": 20,
              "weight": 5
            },
            {
              "id": 1988,
              "amount": 250,
              "weight": 5
            },
            {
              "id": 12934,
              "amount": 500,
              "weight": 3
            },
            {
              "id": 1392,
              "amount": 10,
              "weight": 3
            },
            {
              "id": 5953,
              "amount": 10,
              "weight": 3
            },
            {
              "id": 392,
              "amount": 35,
              "weight": 3
            },
            {
              "id": 6333,
              "amount": 50,
              "weight": 3
            },
            {
              "id": 1939,
              "amount": 1000,
              "weight": 3
            },
            {
              "id": 5075,
              "amount": 10,
              "weight": 3
            },
            {
              "id": 2362,
              "amount": 20,
              "weight": 3
            }
          ],
          "tables": []
        },
        {
          "name": "Fkn rare",
          "weight": 1,
          "items": [
            {
              "id": 12936,
              "amount": 1,
              "weight": 4
            },
            {
              "id": 13200,
              "amount": 1,
              "weight": 1
            },
            {
              "id": 13201,
              "amount": 1,
              "weight": 1
            }
          ],
          "tables": []
        }
      ]
    }
  ]
}
